olympyad/__init__.py
olympyad/compose_functions.py
olympyad-0.0.3.dist-info/LICENSE
olympyad-0.0.3.dist-info/METADATA
olympyad-0.0.3.dist-info/WHEEL
olympyad-0.0.3.dist-info/top_level.txt
olympyad-0.0.3.dist-info/RECORD
