Metadata-Version: 2.1
Name: olympyad
Version: 0.0.3
Summary: A collection of some gist post
Home-page: https://github.com/thorwhalen/newut/tree/master/olympyad
Author: Thor Whalen
License: mit
Platform: any
License-File: LICENSE
